nimrodel_fixed/__init__.py
nimrodel_fixed/_api.py
nimrodel_fixed/_apifunction.py
nimrodel_fixed/_apiobject.py
nimrodel_fixed/_apirest.py
nimrodel_fixed/_misc.py
nimrodel_fixed/output/__init__.py
nimrodel_fixed/output/json.py
nimrodel_fixed/output/xml.py
nimrodel_fixed/res/apiexplorer.jinja
nimrodel_fixed/res/apiexplorer.pyhp
nimrodel_fixed/res/apiexplorer_endpoint.jinja
nimrodel_fixed/res/apiexplorer_endpoint.pyhp
nimrodel_fixed/res/apiexplorer_object.jinja
nimrodel_fixed/res/apiexplorer_object.pyhp
nimrodel_fixed/res/apiexplorer_rest.jinja
nimrodel_fixed/res/apiexplorer_rest.pyhp
nimrodel_fixed-0.8.3.dist-info/LICENSE
nimrodel_fixed-0.8.3.dist-info/WHEEL
nimrodel_fixed-0.8.3.dist-info/METADATA
nimrodel_fixed-0.8.3.dist-info/RECORD
