Metadata-Version: 2.1
Name: nimrodel-fixed
Version: 0.8.3
Summary: Bottle-wrapper to make python objects accessible via HTTP API
Keywords: library,api
Author-email: Johannes Krattenmacher <nimrodel@dev.krateng.ch>, Changjian Gao <gaochangjian@gmail.com>
Requires-Python: >=3.6
Classifier: Programming Language :: Python :: 3
Classifier: License :: OSI Approved :: GNU General Public License v3 (GPLv3)
Classifier: Operating System :: OS Independent
Requires-Dist: bottle
Requires-Dist: waitress
Requires-Dist: doreah>=1.2.1
Requires-Dist: parse
Project-URL: documentation, https://github.com/xiaogaozi/nimrodel
Project-URL: homepage, https://github.com/xiaogaozi/nimrodel
Project-URL: repository, https://github.com/xiaogaozi/nimrodel
